{
  "content": [
    {
      "content": null,
      "created": "2022-07-14T15:44:05.027998Z",
      "format": null,
      "last_modified": "2022-07-14T15:43:00.578912Z",
      "mimetype": null,
      "name": "iwren.ipynb",
      "path": "examples/xeus-wren/iwren.ipynb",
      "size": 3010,
      "type": "notebook",
      "writable": true
    }
  ],
  "created": "2022-07-14T15:44:05.027998Z",
  "format": "json",
  "last_modified": "2022-07-14T15:44:05.027998Z",
  "mimetype": null,
  "name": "xeus-wren",
  "path": "examples/xeus-wren",
  "size": null,
  "type": "directory",
  "writable": true
}